rmqaio/__init__.py
rmqaio/locales/rmqaio.pot
rmqaio/locales/ru/LC_MESSAGES/rmqaio.mo
rmqaio/locales/ru/LC_MESSAGES/rmqaio.po
rmqaio/rmqaio.py
rmqaio-0.16.0.dist-info/LICENSE
rmqaio-0.16.0.dist-info/METADATA
rmqaio-0.16.0.dist-info/WHEEL
rmqaio-0.16.0.dist-info/RECORD
